Workbook

Sheet Instructions
A1: Marymia Ltd – Vendor Security Due Diligence & Weighted Risk Scoring Framework
A3: Prepared by | B3: Ikuomola Adedeji – Third-Party Risk Analyst, Marymia Ltd
A4: Reviewed by | B4: Lara James – Compliance Manager
A5: Version | B5: 1.0
A6: Issue Date | B6: 10 July 2024
A7: Next Review Date | B7: 10 July 2025
A8: Scope | B8: This framework is used to assess the security, privacy, resilience, and compliance posture of third-party vendors providing services to Marymia Ltd.
A10: Version Control
A11: Version | B11: Date | C11: Change Description | D11: Author | E11: Reviewer
A12: 1.0 | B12: 10 Jul 2024 | C12: Initial Issue – Framework Rollout | D12: I. Adedeji | E12: L. James
A13: 1.1 | C13: Annual Update / Vendor Review
A16: Scoring Scale (Industry Standard)
A17: Score | B17: Definition
A18: 5 | B18: Fully implemented, monitored, independently certified (ISO27001/SOC2). Minimal residual risk.
A19: 4 | B19: Implemented and monitored. Evidence available. Low residual risk.
A20: 3 | B20: Partially implemented / gaps documented. Moderate residual risk.
A21: 2 | B21: Ad-hoc / planned but not enforced. High residual risk.
A22: 1 | B22: Not implemented. Critical risk.
A23: 0 | B23: Not applicable to this service.
A26: Audit Evidence References
A27: Evidence Type | B27: Storage Location | C27: Retention Period | D27: Owner
A28: Signed Vendor Contracts | B28: SharePoint / Compliance / Vendors / Contracts / | C28: 7 years | D28: Procurement Manager
A29: Due Diligence Responses | B29: SharePoint / Compliance / Vendors / DDQ2024 / | C29: 3 years | D29: TPRM Analyst
A30: Assessment Reports | B30: SharePoint / Compliance / Vendors / RiskReports / | C30: 3 years | D30: Risk Team Lead
A31: Meeting Minutes / Approvals | B31: Teams / RiskCommittee / TPRMMeetings / | C31: 3 years | D31: Head of Risk
A32: Remediation Trackers | B32: SharePoint / Compliance / Vendors / RemediationPlans / | C32: Until closure | D32: TPRM Analyst

Sheet Questionnaire
A1: Domain | B1: Question | C1: Vendor Response (Y/N/Text) | D1: Evidence Provided | E1: Reviewer Notes | F1: Score (0–5)
A2: Governance & Management | B2: Do you have a documented Information Security Policy approved by senior management?
A3: Governance & Management | B3: Is there an appointed CISO or Security Officer?
A4: Governance & Management | B4: Is information security risk reviewed at least annually by leadership?
A5: Governance & Management | B5: Do you maintain an enterprise risk register that includes third-party risk?
A6: Governance & Management | B6: Do you have a formal change control / CAB process?
A7: Governance & Management | B7: Do you conduct internal security audits or risk assessments?
A8: Governance & Management | B8: Is there defined ownership for security controls?
A9: Governance & Management | B9: Do you have a formal data classification policy?
A10: Governance & Management | B10: Is there a defined Acceptable Use Policy for staff?
A11: Governance & Management | B11: Do you require employees to sign confidentiality / NDA agreements?
A12: Data Protection & Privacy | B12: Do you process personal data on behalf of Marymia Ltd?
A13: Data Protection & Privacy | B13: Are you GDPR compliant?
... A81: Physical Security & Facilities | B81: Are cleaning/maintenance staff vetted where they have access to sensitive areas?

Sheet Weighted Scoring Model
A1: Domain | B1: Average Score (0-5) | C1: Weight (%) | D1: Weighted Contribution | E1: Risk Bucket (Auto)
A2: Governance & Management | B2: =AVERAGEIF(Questionnaire!F2:F11,">=0") | C2: 10 | D2: =B2*C2/100 | E2: =IF(B2>=4,"Low",IF(B2>=3,"Medium","High"))
A3: Data Protection & Privacy | B3: =AVERAGEIF(Questionnaire!F12:F23,">=0") | C3: 15 | D3: =B3*C3/100 | E3: =IF(B3>=4,"Low",IF(B3>=3,"Medium","High"))
A4: Access & Identity Management | B4: =AVERAGEIF(Questionnaire!F24:F31,">=0") | C4: 10 | D4: =B4*C4/100 | E4: =IF(B4>=4,"Low",IF(B4>=3,"Medium","High"))
A5: Network & Infrastructure Security | B5: =AVERAGEIF(Questionnaire!F32:F41,">=0") | C5: 10 | D5: =B5*C5/100 | E5: =IF(B5>=4,"Low",IF(B5>=3,"Medium","High"))
A6: Application Security | B6: =AVERAGEIF(Questionnaire!F42:F49,">=0") | C6: 10 | D6: =B6*C6/100 | E6: =IF(B6>=4,"Low",IF(B6>=3,"Medium","High"))
A7: Incident Response & BCP / DR | B7: =AVERAGEIF(Questionnaire!F50:F60,">=0") | C7: 15 | D7: =B7*C7/100 | E7: =IF(B7>=4,"Low",IF(B7>=3,"Medium","High"))
A8: Compliance & Certifications | B8: =AVERAGEIF(Questionnaire!F61:F66,">=0") | C8: 10 | D8: =B8*C8/100 | E8: =IF(B8>=4,"Low",IF(B8>=3,"Medium","High"))
A9: Subprocessors / Third Parties | B9: =AVERAGEIF(Questionnaire!F67:F72,">=0") | C9: 8 | D9: =B9*C9/100 | E9: =IF(B9>=4,"Low",IF(B9>=3,"Medium","High"))
A10: Training & Awareness | B10: =AVERAGEIF(Questionnaire!F73:F76,">=0") | C10: 7 | D10: =B10*C10/100 | E10: =IF(B10>=4,"Low",IF(B10>=3,"Medium","High"))
A11: Physical Security & Facilities | B11: =AVERAGEIF(Questionnaire!F77:F81,">=0") | C11: 5 | D11: =B11*C11/100 | E11: =IF(B11>=4,"Low",IF(B11>=3,"Medium","High"))
A13: TOTAL WEIGHTED SCORE | B13: =SUM(D2:D11) | C13: Overall Risk Rating | D13: =IF(B13>=4,"Low",IF(B13>=3,"Medium","High"))

Sheet Vendor Summary
A1: Vendor | B1: Service Type | C1: Date Sent | D1: Response Date | E1: Reviewed By | F1: Weighted Score | G1: Overall Risk | H1: Next Review Date | I1: Key Gaps / Notes | J1: Recommendation
A2: AWS (Amazon Web Services) | B2: Cloud Hosting & Infrastructure | C2: 10-Jul-2024 | D2: 17-Jul-2024 | E2: Ikuomola Adedeji | F2: 4.6 | G2: Low | H2: 10-Jul-2025 | I2: Strong ISO/SOC posture | J2: Maintain service
A3: Microsoft Azure | B3: Cloud Hosting & Identity | C3: 10-Jul-2024 | D3: 17-Jul-2024 | E3: Ikuomola Adedeji | F3: 4.5 | G3: Low | H3: 10-Jul-2025 | I3: Mature access controls/MFA enforced | J3: Maintain
A4: Google Workspace | B4: Productivity & Email | C4: 10-Jul-2024 | D4: 17-Jul-2024 | E4: Ikuomola Adedeji | F4: 3.9 | G4: Medium | H4: 10-Jul-2025 | I4: Shared tenancy risk | J4: Monitor config reviews
A5: Cisco Systems | B5: Networking & Security | C5: 10-Jul-2024 | D5: 17-Jul-2024 | E5: Ikuomola Adedeji | F5: 3.7 | G5: Medium | H5: 10-Jul-2025 | I5: Patch mgmt cadence monthly | J5: Accept w/ monitoring
A6: Dell Technologies | B6: Hardware & Support | C6: 10-Jul-2024 | D6: 17-Jul-2024 | E6: Ikuomola Adedeji | F6: 3.5 | G6: Medium | H6: 10-Jul-2025 | I6: Limited breach notification SLA | J6: Add contract clause
A7: Salesforce | B7: CRM Platform | C7: 10-Jul-2024 | D7: 17-Jul-2024 | E7: Ikuomola Adedeji | F7: 4.2 | G7: Low | H7: 10-Jul-2025 | I7: Customer data encryption, SOC2 | J7: Maintain
A8: Workday | B8: HR & Payroll Platform | C8: 10-Jul-2024 | D8: 17-Jul-2024 | E8: Ikuomola Adedeji | F8: 3.6 | G8: Medium | H8: 10-Jul-2025 | I8: BCP tested annually | J8: Mitigate minor gaps
A9: ServiceNow | B9: ITSM Platform | C9: 10-Jul-2024 | D9: 17-Jul-2024 | E9: Ikuomola Adedeji | F9: 3.4 | G9: Medium | H9: 10-Jul-2025 | I9: Breach notification 48h not 24h | J9: Update SLA
A10: Slack | B10: Collaboration Tool | C10: 10-Jul-2024 | D10: 17-Jul-2024 | E10: Ikuomola Adedeji | F10: 3.2 | G10: Medium | H10: 10-Jul-2025 | I10: No ISO cert provided | J10: Request evidence
A11: Zoom | B11: Video Conferencing | C11: 10-Jul-2024 | D11: 17-Jul-2024 | E11: Ikuomola Adedeji | F11: 3.1 | G11: Medium | H11: 10-Jul-2025 | I11: Data residency concerns | J11: Monitor
A12: CrowdStrike | B12: Endpoint Security | C12: 10-Jul-2024 | D12: 17-Jul-2024 | E12: Ikuomola Adedeji | F12: 4.4 | G12: Low | H12: 10-Jul-2025 | I12: Strong IR capability | J12: Maintain
A13: Okta | B13: Identity & Access Management | C13: 10-Jul-2024 | D13: 17-Jul-2024 | E13: Ikuomola Adedeji | F13: 4.3 | G13: Low | H13: 10-Jul-2025 | I13: Privileged access controls mature | J13: Maintain
... A31: Mailchimp | B31: Marketing Automation | C31: 10-Jul-2024 | D31: 17-Jul-2024 | E31: Ikuomola Adedeji | F31: 3.1 | G31: Medium | H31: 10-Jul-2025 | I31: Subscriber PII exposure | J31: Limit data shared

Sheet Dashboard
A1: Marymia Ltd – DDQ Status Dashboard
A3: Total Vendors in Scope | B3: =COUNTA('Vendor Summary'!A2:A31)
A4: Responses Received | B4: =COUNTA('Vendor Summary'!D2:D31)
A5: Response Rate % | B5: =IF(B4=0,0,B5/B4)
A6: Average Weighted Score | B6: =AVERAGE('Vendor Summary'!F2:F31)
A7: Low Risk Vendors | B7: =COUNTIF('Vendor Summary'!G2:G31,"Low")
A8: Medium Risk Vendors | B8: =COUNTIF('Vendor Summary'!G2:G31,"Medium")
A9: High Risk Vendors | B9: =COUNTIF('Vendor Summary'!G2:G31,"High")
A10: Next Review Cycle | B10: 10-Jul-2025
